zonevu/Zonevu.py
zonevu/Zonevu.pyi
zonevu/__init__.py
zonevu/__init__.pyi
zonevu/datamodels/Company.py
zonevu/datamodels/Company.pyi
zonevu/datamodels/DataModel.py
zonevu/datamodels/DataModel.pyi
zonevu/datamodels/Document.py
zonevu/datamodels/Document.pyi
zonevu/datamodels/Helpers.py
zonevu/datamodels/Helpers.pyi
zonevu/datamodels/PrimaryDataObject.py
zonevu/datamodels/PrimaryDataObject.pyi
zonevu/datamodels/Project.py
zonevu/datamodels/Project.pyi
zonevu/datamodels/__init__.py
zonevu/datamodels/__init__.pyi
zonevu/datamodels/completions/DepthFeature.py
zonevu/datamodels/completions/DepthFeature.pyi
zonevu/datamodels/completions/Frac.py
zonevu/datamodels/completions/Frac.pyi
zonevu/datamodels/completions/FracEntry.py
zonevu/datamodels/completions/FracEntry.pyi
zonevu/datamodels/completions/Plug.py
zonevu/datamodels/completions/Plug.pyi
zonevu/datamodels/completions/Stage.py
zonevu/datamodels/completions/Stage.pyi
zonevu/datamodels/completions/UserDefinedStageValue.py
zonevu/datamodels/completions/UserDefinedStageValue.pyi
zonevu/datamodels/completions/__init__.py
zonevu/datamodels/completions/__init__.pyi
zonevu/datamodels/geomodels/DataGrid.py
zonevu/datamodels/geomodels/DataGrid.pyi
zonevu/datamodels/geomodels/Geomodel.py
zonevu/datamodels/geomodels/Geomodel.pyi
zonevu/datamodels/geomodels/GriddedData.py
zonevu/datamodels/geomodels/GriddedData.pyi
zonevu/datamodels/geomodels/SimpleGrid.py
zonevu/datamodels/geomodels/SimpleGrid.pyi
zonevu/datamodels/geomodels/Structure.py
zonevu/datamodels/geomodels/Structure.pyi
zonevu/datamodels/geomodels/__init__.py
zonevu/datamodels/geomodels/__init__.pyi
zonevu/datamodels/geospatial/Coordinate.py
zonevu/datamodels/geospatial/Coordinate.pyi
zonevu/datamodels/geospatial/Crs.py
zonevu/datamodels/geospatial/Crs.pyi
zonevu/datamodels/geospatial/CrsDescriptor.py
zonevu/datamodels/geospatial/CrsDescriptor.pyi
zonevu/datamodels/geospatial/Enums.py
zonevu/datamodels/geospatial/Enums.pyi
zonevu/datamodels/geospatial/GeoBox.py
zonevu-2.0.20.dist-info/METADATA
zonevu-2.0.20.dist-info/WHEEL
zonevu-2.0.20.dist-info/entry_points.txt
zonevu-2.0.20.dist-info/licenses/LICENSE
zonevu-2.0.20.dist-info/RECORD
