Metadata-Version: 2.4
Name: zonevu
Version: 2.0.20
Summary: ZoneVu Web API Python SDK Package
License: Proprietary
License-File: LICENSE
Author: Ubiterra
Author-email: support@ubiterra.com
Requires-Python: >=3.10,<4.0
Classifier: Development Status :: 4 - Beta
Classifier: Intended Audience :: Developers
Classifier: License :: Other/Proprietary License
Classifier: Programming Language :: Python :: 3
Classifier: Programming Language :: Python :: 3.10
Classifier: Programming Language :: Python :: 3.11
Classifier: Programming Language :: Python :: 3.12
Classifier: Programming Language :: Python :: 3.13
Classifier: Programming Language :: Python :: 3.14
Classifier: Topic :: Software Development :: Libraries
Requires-Dist: dataclasses-json (>=0.6.7,<0.7.0)
Requires-Dist: numpy (>=2.0.0,<3.0.0)
Requires-Dist: pygeojson (>=0.2.0,<0.3.0)
Requires-Dist: requests (>=2.32.4,<3.0.0)
Requires-Dist: strenum (>=0.4.15,<0.5.0)
Requires-Dist: tomlkit (>=0.13.2,<0.14.0)
Project-URL: Documentation-Versioned, https://zonevu.ubiterra.com/Help/Html/ZonevuPythonSDK/2.0.20/index.html
Project-URL: Documentation, https://help.ubiterra.com/help/zonevu-python-library
Project-URL: Homepage, https://www.ubiterra.com/
